appengine_sdk
